{
    "description": "",
    "prefix": "action_restinsettlement",
    "types": {
        "start": {
            "description": "",
            "variables": ["hero"],
            "phrases": [
                "[[hero|и.п.]] [[hero|род|решил]] отдухонуть и залечить раны",
                "[[hero|род|отправился]] искать подорожник",
                "Йод, касторка, спирт, теперь надо всё это смешать и выпить, глядишь - поможет"
            ]
        },
        "resring": {
            "description": "",
            "variables": ["hero", "health"],
            "phrases": [
                "Ух ты, а подорожник помогает, вылечил %(health)d HP",
                "[[hero|род|применил]] магию вуду и [[hero|род|исцелился]] на %(health)d HP",
                "Проходящий мимо шаман кастанул чайник и исцелил на %(health)d HP"
            ]
        }
    }
}