{
    "description": "",
    "prefix": "action_inplace",
    "types": {
        "description": {
            "description": "",
            "variables": {"hero": "привидение", "place": "город"},
            "phrases": [
                ["изучает окрестности",
                 "изучает окрестности"]
            ]
        },
        "spend_useless": {
            "description": "",
            "variables": {"hero": "привидение", "coins": 113},
            "phrases": [
                ["[{Рассыпал|hero|прш}] монеты по мостовой, собрав, [{недосчитался|hero|прш}] [[coins]] [{штука|coins|}]",
                 "рассыпало монеты по мостовой, собрав, недосчиталось 113 штук"],
                ["[{Купил|hero|прш}] билеты в цирк, всего-то [[coins]] [{монета|coins|}]",
                 "купило билеты в цирк, всего-то 113 монет"]
            ]
        },
        "instant_heal": {
            "description": "",
            "variables": {"hero": "привидение", "coins": 13},
            "phrases": [
                ["Лекарь содрал [[coins]] [{монета|coins|}] за лечение",
                 "лекарь содрал 13 монет за лечение"]
            ]
        },
        "buying_artifact": {
            "description": "",
            "variables": {"hero": "привидение", "coins": 13, "artifact": "пепельница"},
            "phrases": [
                ["Торговка впарила [[artifact|вн]] за [{целый|coins|}] [[coins]] [{монета|coins|}]",
                 "Торговка впарила пепельницу за целых 13 монет"]
            ]
        },
        "sharpening_artifact": {
            "description": "",
            "variables": {"hero": "привидение", "coins": 13, "artifact": "пепельница"},
            "phrases": [
                ["[{Заплатил|hero|прш}] кузнецу [[coins]] [{монета|coins|}] за улучшение [[artifact|рд]]",
                 "Заплатило кузнецу 13 монет за улучшение пепельницы"]
            ]
        },
        "impact_good": {
            "description": "",
            "variables": {"hero": "привидение", "coins": 13, "person": "гусь"},
            "phrases": [
                ["[{Отдал|hero|прш}] [[coins]] [{монета|coins|}] [[person||дт]] - на благое дело",
                 "отдало 13 монет гусю - на благое дело"]
            ]
        },
        "impact_bad": {
            "description": "",
            "variables": {"hero": "привидение", "coins": 13, "person": "гусь"},
            "phrases": [
                ["[{Заплатил|hero|прш}] [[coins]] [{монета|coins|}] специально обученным людям - посмотрим, как это понравится [[person||дт]]",
                 "заплатило 13 монет специально обученным людям - посмотрим, как это понравится гусю"]
            ]
        }
    }
}
